clickr_logger/__init__.py
clickr_logger-0.1.0.dist-info/WHEEL
clickr_logger-0.1.0.dist-info/METADATA
clickr_logger-0.1.0.dist-info/RECORD
