Metadata-Version: 2.1
Name: clickr-logger
Version: 0.1.0
Summary: Common logger functions for clickr
Author: Grzegorz Bajson
Author-email: gbajson@protonmail.ch
Requires-Python: >=3.7,<4.0
Classifier: Programming Language :: Python :: 3
Classifier: Programming Language :: Python :: 3.7
Classifier: Programming Language :: Python :: 3.8
Classifier: Programming Language :: Python :: 3.9
Requires-Dist: loguru (>=0.5.3,<0.6.0)
